magicfile-0.4.27.dist-info/RECORD
magicfile-0.4.27.dist-info/LICENSE
magicfile-0.4.27.dist-info/WHEEL
magicfile-0.4.27.dist-info/top_level.txt
magicfile-0.4.27.dist-info/METADATA
magicfile/_libmagic.abi3.so
magicfile/__init__.py
magicfile/magic.mgc
magicfile/_libmagic_build.py
magicfile/.dylibs/libmagic.1.dylib
