Metadata-Version: 2.1
Name: magicfile
Version: 0.4.27
Summary: File type identification using libmagic
Home-page: http://github.com/messense/magicfile
Author: Adam Hupp
Author-email: adam@hupp.org
License: MIT
Keywords: mime magic file
Platform: UNKNOWN
Classifier: Intended Audience :: Developers
Classifier: License :: OSI Approved :: MIT License
Classifier: Programming Language :: Python
Classifier: Programming Language :: Python :: 2
Classifier: Programming Language :: Python :: 2.7
Classifier: Programming Language :: Python :: 3
Classifier: Programming Language :: Python :: 3.6
Classifier: Programming Language :: Python :: Implementation :: CPython
Requires-Dist: cffi (>=1.0.0)
